octoprint_simplyprint/__init__.py
octoprint_simplyprint/comm/__init__.py
octoprint_simplyprint/comm/constants.py
octoprint_simplyprint/comm/monitor.py
octoprint_simplyprint/comm/util.py
octoprint_simplyprint/static/css/SimplyPrint.css
octoprint_simplyprint/static/font/lcd.ttf
octoprint_simplyprint/static/img/sp_logo.png
octoprint_simplyprint/static/img/sp_logo_large.png
octoprint_simplyprint/static/img/sp_white_sm.png
octoprint_simplyprint/static/js/SimplyPrint.js
octoprint_simplyprint/templates/SimplyPrint.jinja2
octoprint_simplyprint/templates/SimplyPrint_navbar.jinja2
octoprint_simplyprint/templates/SimplyPrint_settings.jinja2
octoprint_simplyprint/websocket/__init__.py
octoprint_simplyprint/websocket/constants.py
octoprint_simplyprint/websocket/file_handler.py
octoprint_simplyprint/websocket/simplyprint.py
octoprint_simplyprint/websocket/system.py
octoprint_simplyprint/websocket/webcam.py
SimplyPrint-4.1.2.dist-info/LICENSE
SimplyPrint-4.1.2.dist-info/METADATA
SimplyPrint-4.1.2.dist-info/WHEEL
SimplyPrint-4.1.2.dist-info/entry_points.txt
SimplyPrint-4.1.2.dist-info/top_level.txt
SimplyPrint-4.1.2.dist-info/RECORD
