Metadata-Version: 2.1
Name: SimplyPrint
Version: 4.1.2
Summary: 3D print online anywhere from (probably) the most user friendly all-in-one platform there is, from your computer or phone.
Home-page: https://simplyprint.io/
Author: SimplyPrint
Author-email: albert@simplyprint.io
License: AGPLv3
License-File: LICENSE
Requires-Dist: OctoPrint
Requires-Dist: requests
Requires-Dist: python-crontab
Requires-Dist: distro
Requires-Dist: sentry-sdk
